README.rst
setup.py
rugplot/__init__.py
rugplot.egg-info/PKG-INFO
rugplot.egg-info/SOURCES.txt
rugplot.egg-info/dependency_links.txt
rugplot.egg-info/not-zip-safe
rugplot.egg-info/requires.txt
rugplot.egg-info/top_level.txt