Metadata-Version: 1.1
Name: rugplot
Version: 0.8.1
Summary: SVG RugPlot Python API
Home-page: http://github.com/CSB-IG/rugplot
Author: Rodrigo Garcia
Author-email: rgarcia@inmegen.gob.mx
License: GPLv3
Platform: UNKNOWN
Classifier: License :: OSI Approved :: GNU General Public License v3 (GPLv3)
Classifier: Programming Language :: Python :: 2.7
Classifier: Topic :: Scientific/Engineering :: Information Analysis
Classifier: Intended Audience :: Science/Research
Classifier: Topic :: Scientific/Engineering
